fucker/__init__.py
fucker/wp.py
fucker-11.0.dist-info/LICENSE
fucker-11.0.dist-info/METADATA
fucker-11.0.dist-info/WHEEL
fucker-11.0.dist-info/top_level.txt
fucker-11.0.dist-info/RECORD
